pysare/__init__.py
pysare/_typing.py
pysare/age_replacement/__init__.py
pysare/age_replacement/_sequential_finite_horizon.py
pysare/data/Dataset.py
pysare/data/__init__.py
pysare/data/datasets/WeibullUniformParameters.py
pysare/data/datasets/_SimulatedCategoricalWeibull.py
pysare/data/datasets/__init__.py
pysare/evaluation/QQ_plot.py
pysare/evaluation/__init__.py
pysare/evaluation/binomial_log_likelihood.py
pysare/evaluation/brier_score.py
pysare/evaluation/concordance_index.py
pysare/evaluation/negative_log_likelihood.py
pysare/models/SurvivalModel.py
pysare/models/_KaplanMeier.py
pysare/models/__init__.py
pysare/models/ensemble.py
pysare/models/_numpy/NumpySurvivalModel.py
pysare/models/_numpy/__init__.py
pysare/models/distributions/_Uniform.py
pysare/models/distributions/_Weibull.py
pysare/models/distributions/__init__.py
pysare/models/energy_based/EnergyBasedDensity.py
pysare/models/energy_based/__init__.py
pysare/models/energy_based/integrators/_Integrator.py
pysare/models/energy_based/integrators/__init__.py
pysare/models/mixture/GaussianMixture.py
pysare/models/mixture/WeibullMixture.py
pysare/models/mixture/_MixtureSurvivalModel.py
pysare/models/mixture/__init__.py
pysare/models/mixture/_mixers/_Mixer.py
pysare/models/mixture/_mixers/__init__.py
pysare/models/piecewise/_ConstantDensity.py
pysare/models/piecewise/_ConstantHazard.py
pysare/models/piecewise/_LinearDensity.py
pysare/models/piecewise/_LinearHazard.py
pysare/models/piecewise/__init__.py
pysare/models/piecewise/grid/__init__.py
pysare/models/piecewise/grid/_grid.py
pysare/models/utils/MLP.py
pysare/models/utils/__init__.py
pysare/reliability/__init__.py
pysare/reliability/renewal_function.py
pysare/reliability/age_replacement/__init__.py
pysare/reliability/age_replacement/random_exponential_horizon.py
pysare/reliability/age_replacement/sequential_finite_horizon.py
pysare/reliability/age_replacement/sequential_random_horizon.py
pysare/reliability/age_replacement/simulate.py
pysare-0.1.2.dist-info/LICENSE
pysare-0.1.2.dist-info/METADATA
pysare-0.1.2.dist-info/WHEEL
pysare-0.1.2.dist-info/top_level.txt
pysare-0.1.2.dist-info/RECORD
