Metadata-Version: 2.1
Name: pysare
Version: 0.1.2
Summary: PySaRe -- Neural Network-Based Survival Analysis and Reliability Engineering
Home-page: https://github.com/oholmer/PySaRe
Author: Olov Holmer
Author-email: olov.holmer@liu.se
Project-URL: Bug Tracker, https://github.com/oholmer/PySaRe/issues
Classifier: Programming Language :: Python :: 3
Classifier: License :: OSI Approved :: MIT License
Classifier: Operating System :: OS Independent
Requires-Python: >=3.10
License-File: LICENSE
Requires-Dist: numpy >=1.14.0
Requires-Dist: torch >=0.4.1
Requires-Dist: pandas >=2.1
Requires-Dist: matplotlib >=3.0
Requires-Dist: torch-lr-finder >=0.2.1
Requires-Dist: scipy >=1.7.0
Requires-Dist: lifelines >=0.29.0
